test/__init__.py
test/test_db.py
test/test_npm.py
test/test_source.py
test/test_storage.py
test/test_utils.py
vulndb/__init__.py
vulndb/cli.py
vulndb/lib/__init__.py
vulndb/lib/config.py
vulndb/lib/db.py
vulndb/lib/gha.py
vulndb/lib/npm.py
vulndb/lib/nvd.py
vulndb/lib/storage.py
vulndb/lib/utils.py
appthreat_vulndb-1.0.4.dist-info/LICENSE
appthreat_vulndb-1.0.4.dist-info/METADATA
appthreat_vulndb-1.0.4.dist-info/WHEEL
appthreat_vulndb-1.0.4.dist-info/entry_points.txt
appthreat_vulndb-1.0.4.dist-info/top_level.txt
appthreat_vulndb-1.0.4.dist-info/RECORD
