Metadata-Version: 2.1
Name: appthreat-vulndb
Version: 1.0.4
Summary: Vulnerability database and package search for sources such as CVE, GitHub, and so on. Uses a built-in file based storage.
Home-page: https://github.com/appthreat/vulndb
Author: Team AppThreat
Author-email: cloud@appthreat.com
License: UNKNOWN
Platform: UNKNOWN
Classifier: Development Status :: 5 - Production/Stable
Classifier: Intended Audience :: Developers
Classifier: Intended Audience :: System Administrators
Classifier: Topic :: Utilities
Classifier: Topic :: Security
Classifier: Programming Language :: Python :: 3.6
Classifier: Programming Language :: Python :: 3.7
Classifier: Programming Language :: Python :: 3.8
Classifier: License :: OSI Approved :: MIT License
Classifier: Operating System :: OS Independent
Requires-Python: >=3.6
Requires-Dist: requests
Requires-Dist: appdirs
Requires-Dist: tabulate
Requires-Dist: msgpack
